mysaft/__init__.py
mysaft/example.py
raaSAFT-0.6.4.dist-info/DESCRIPTION.rst
raaSAFT-0.6.4.dist-info/METADATA
raaSAFT-0.6.4.dist-info/RECORD
raaSAFT-0.6.4.dist-info/WHEEL
raaSAFT-0.6.4.dist-info/entry_points.txt
raaSAFT-0.6.4.dist-info/metadata.json
raaSAFT-0.6.4.dist-info/top_level.txt
raasaft/__init__.py
raasaft/acids.py
raasaft/alcohols.py
raasaft/alkanes.py
raasaft/aromatic.py
raasaft/constants.py
raasaft/crude.py
raasaft/dirinit.py
raasaft/gases.py
raasaft/main.py
raasaft/mie.py
raasaft/sulfuric.py
raasaft/surfactants.py
raasaft/water.py
