Metadata-Version: 2.0
Name: raaSAFT
Version: 0.6.4
Summary: Coarse-grained simulations with the SAFT-gamma Mie force field
Home-page: https://bitbucket.org/asmunder/raasaft/
Author: Åsmund Ervik
Author-email: aaervik@gmail.com
License: MIT
Keywords: molecular dynamics GPU SAFT Mie HOOMD
Platform: UNKNOWN
Classifier: Development Status :: 4 - Beta
Classifier: Intended Audience :: Science/Research
Classifier: Topic :: Scientific/Engineering :: Chemistry
Classifier: Topic :: Scientific/Engineering :: Physics
Classifier: License :: OSI Approved :: MIT License
Classifier: Programming Language :: Python :: 2
Classifier: Programming Language :: Python :: 2.7
Classifier: Programming Language :: Python :: 3
Classifier: Programming Language :: Python :: 3.2
Classifier: Programming Language :: Python :: 3.3
Classifier: Programming Language :: Python :: 3.4
Classifier: Programming Language :: Python :: 3.5
Requires-Dist: future
Requires-Dist: requests
